etherrain/__init__.py
etherrain/__main__.py
etherrain/etherrain.py
etherrain-0.6.dist-info/DESCRIPTION.rst
etherrain-0.6.dist-info/LICENSE.txt
etherrain-0.6.dist-info/METADATA
etherrain-0.6.dist-info/RECORD
etherrain-0.6.dist-info/WHEEL
etherrain-0.6.dist-info/metadata.json
etherrain-0.6.dist-info/top_level.txt
