Metadata-Version: 2.0
Name: etherrain
Version: 0.6
Summary: Interface Library for QuickSmart Etherrain/8 irrigation controller
Home-page: https://github.com/hpeyerl/etherrain
Author: Herb Peyerl
Author-email: hpeyerl+etherrain@beer.org
Maintainer: Herb Peyerl
Maintainer-email: hpeyerl+etherrain@beer.org
License: MIT
Keywords: irrigation,watering
Platform: UNKNOWN
Classifier: Intended Audience :: Developers
Classifier: Programming Language :: Python
Classifier: Programming Language :: Python :: 2
Classifier: Programming Language :: Python :: 2.7
Classifier: Programming Language :: Python :: 3
Classifier: Programming Language :: Python :: 3.3
Classifier: Programming Language :: Python :: 3.4
Classifier: Programming Language :: Python :: 3.5
Classifier: License :: OSI Approved :: MIT License
Requires-Dist: requests (>=2.5.4)
